{
  "id": "modules/memory/providers/index",
  "title": "Memory Providers",
  "description": "Available memory storage providers",
  "source": "@site/docs/06-modules/memory/providers/index.md",
  "sourceDirName": "06-modules/memory/providers",
  "slug": "/modules/memory/providers/",
  "permalink": "/docs/modules/memory/providers/",
  "draft": false,
  "unlisted": false,
  "editUrl": "https://github.com/symindx/symindx/tree/main/docs-site/docs/06-modules/memory/providers/index.md",
  "tags": [],
  "version": "current",
  "lastUpdatedBy": "SYMBaiEX",
  "lastUpdatedAt": 1751440259000,
  "sidebarPosition": 1,
  "frontMatter": {
    "sidebar_position": 1,
    "title": "Memory Providers",
    "description": "Available memory storage providers"
  },
  "sidebar": "docsSidebar",
  "previous": {
    "title": "Memory Modules",
    "permalink": "/docs/modules/memory/"
  },
  "next": {
    "title": "SQLite Memory Provider",
    "permalink": "/docs/modules/memory/sqlite/"
  }
}