{
  "id": "getting-started/quick-start/index",
  "title": "Quick Start",
  "description": "Get your first SYMindX agent up and running in just 10 minutes! This guide assumes you've already completed the installation.",
  "source": "@site/docs/getting-started/quick-start/index.md",
  "sourceDirName": "getting-started/quick-start",
  "slug": "/getting-started/quick-start/",
  "permalink": "/docs/getting-started/quick-start/",
  "draft": false,
  "unlisted": false,
  "editUrl": "https://github.com/symindx/symindx/tree/main/docs-site/docs/getting-started/quick-start/index.md",
  "tags": [],
  "version": "current",
  "lastUpdatedBy": "SYMBaiEX",
  "lastUpdatedAt": 1751411341000,
  "frontMatter": {},
  "sidebar": "quickLinksSidebar",
  "previous": {
    "title": "Installation",
    "permalink": "/docs/getting-started/installation/"
  },
  "next": {
    "title": "Your First Agent",
    "permalink": "/docs/getting-started/first-agent/"
  }
}