{
  "id": "core-concepts/lifecycle/index",
  "title": "Lifecycle",
  "description": "Component lifecycle management",
  "source": "@site/docs/core-concepts/lifecycle/index.md",
  "sourceDirName": "core-concepts/lifecycle",
  "slug": "/core-concepts/lifecycle/",
  "permalink": "/docs/core-concepts/lifecycle/",
  "draft": false,
  "unlisted": false,
  "editUrl": "https://github.com/symindx/symindx/tree/main/docs-site/docs/core-concepts/lifecycle/index.md",
  "tags": [],
  "version": "current",
  "lastUpdatedBy": "Author",
  "lastUpdatedAt": 1539502055000,
  "sidebarPosition": 1,
  "frontMatter": {
    "sidebar_position": 1,
    "title": "Lifecycle",
    "description": "Component lifecycle management"
  },
  "sidebar": "docsSidebar",
  "previous": {
    "title": "Plugin System",
    "permalink": "/docs/core-concepts/plugin-system/"
  },
  "next": {
    "title": "Agents",
    "permalink": "/docs/agents/"
  }
}